hunter_api/__init__.py
hunter_api/classes.py
hunter_api-0.2.dist-info/METADATA
hunter_api-0.2.dist-info/WHEEL
hunter_api-0.2.dist-info/top_level.txt
hunter_api-0.2.dist-info/RECORD
