Metadata-Version: 2.1
Name: hunter-api
Version: 0.2
Requires-Dist: requests
